cli/__init__.py
cli/click_utils.py
cli/config.py
cli/fritz_object_selector.py
cli/model.py
cli/print_utils.py
cli/project.py
cli/app/__init__.py
cli/app/android_setup.py
cli/app/app_files.py
cli/app/app_setup.py
cli/app/apps.py
cli/app/code_snippet.py
cli/app/file_manager.py
cli/app/setup_utils.py
cli/app/android/__init__.py
cli/app/android/android_config.py
cli/app/android/android_helpers.py
cli/app/android/android_snippets.py
cli/app/ios/__init__.py
cli/app/ios/ios_config.py
cli/app/ios/ios_helpers.py
cli/app/ios/ios_snippets.py
fritz/__init__.py
fritz/api_client.py
fritz/configuration.py
fritz/errors.py
fritz/feature_type.py
fritz/frameworks.py
fritz/utils.py
fritz/api_resources/__init__.py
fritz/api_resources/app.py
fritz/api_resources/fritz_object.py
fritz/api_resources/model.py
fritz/api_resources/model_grade_report.py
fritz/api_resources/model_snapshot.py
fritz/api_resources/model_version.py
fritz/api_resources/project.py
fritz/train/__init__.py
fritz/train/model_checkpoint.py
fritz-2.3.5.dist-info/METADATA
fritz-2.3.5.dist-info/WHEEL
fritz-2.3.5.dist-info/entry_points.txt
fritz-2.3.5.dist-info/top_level.txt
fritz-2.3.5.dist-info/RECORD
