Metadata-Version: 2.1
Name: fritz
Version: 2.3.5
Summary: Fritz Machine Learning Library.
Home-page: https://github.com/fritzlabs/fritz-python
Author: Fritz Engineering
Author-email: engineering@fritz.ai
License: MIT
Project-URL: Documentation, https://docs.fritz.ai/cli/index.html
Project-URL: Source Code, https://github.com/fritzlabs/fritz-python
Project-URL: Bug Tracker, https://github.com/fritzlabs/fritz-python/issues
Keywords: machine learning,training,app development
Platform: UNKNOWN
Classifier: Intended Audience :: Developers
Classifier: License :: OSI Approved :: MIT License
Classifier: Operating System :: OS Independent
Classifier: Programming Language :: Python :: 3
Classifier: Programming Language :: Python :: 3.4
Classifier: Programming Language :: Python :: 3.5
Classifier: Programming Language :: Python :: 3.6
Classifier: Programming Language :: Python :: 3.7
Provides-Extra: train
